web_asset_vendor/__init__.py
web_asset_vendor/models/__init__.py
web_asset_vendor/models/asset.py
web_asset_vendor/models/fetcher.py
web_asset_vendor/models/resolver.py
web_asset_vendor/utils/__init__.py
web_asset_vendor/utils/exceptions.py
web_asset_vendor/utils/exceptions_runtime.py
web_asset_vendor/utils/regex.py
web_asset_vendor-0.1.0b1.dist-info/METADATA
web_asset_vendor-0.1.0b1.dist-info/WHEEL
web_asset_vendor-0.1.0b1.dist-info/top_level.txt
web_asset_vendor-0.1.0b1.dist-info/RECORD
