Metadata-Version: 2.1
Name: web-asset-vendor
Version: 0.1.0b1
Summary: Downloading assets from the web in a reproducible way
Home-page: https://github.com/funkykay
Author: Kay Donner
Author-email: web-asset-vendor@kaydonner.de
Maintainer: Kay Donner
Maintainer-email: web-asset-vendor@kaydonner.de
License: Apache-2.0
Platform: UNKNOWN
Classifier: Environment :: Web Environment
Classifier: License :: OSI Approved :: Apache Software License
Classifier: Operating System :: OS Independent
Classifier: Programming Language :: Python :: 3.6
Classifier: Programming Language :: Python :: 3.7
Requires-Python: >=3.6
Requires-Dist: requests (==2.25.1)
Requires-Dist: PyYAML (==5.3.1)
